LICENSE
README.md
pyproject.toml
setup.py
clustpy/__init__.py
clustpy.egg-info/PKG-INFO
clustpy.egg-info/SOURCES.txt
clustpy.egg-info/dependency_links.txt
clustpy.egg-info/requires.txt
clustpy.egg-info/top_level.txt
clustpy/alternative/__init__.py
clustpy/alternative/autonr.py
clustpy/alternative/nrkmeans.py
clustpy/alternative/orth.py
clustpy/data/__init__.py
clustpy/data/_utils.py
clustpy/data/preprocessing.py
clustpy/data/real_clustpy_data.py
clustpy/data/real_medical_mnist_data.py
clustpy/data/real_timeseries_data.py
clustpy/data/real_torchvision_data.py
clustpy/data/real_uci_data.py
clustpy/data/real_video_data.py
clustpy/data/real_world_data.py
clustpy/data/synthetic_data_creator.py
clustpy/data/datasets/aloi_small.data
clustpy/data/datasets/fruit.data
clustpy/data/datasets/nrLetters.data
clustpy/data/datasets/stickfigures.data
clustpy/deep/__init__.py
clustpy/deep/_abstract_deep_clustering_algo.py
clustpy/deep/_data_utils.py
clustpy/deep/_early_stopping.py
clustpy/deep/_train_utils.py
clustpy/deep/_utils.py
clustpy/deep/aec.py
clustpy/deep/dcn.py
clustpy/deep/ddc_n2d.py
clustpy/deep/dec.py
clustpy/deep/deepect.py
clustpy/deep/dipdeck.py
clustpy/deep/dipencoder.py
clustpy/deep/dkm.py
clustpy/deep/enrc.py
clustpy/deep/vade.py
clustpy/deep/neural_networks/__init__.py
clustpy/deep/neural_networks/_abstract_autoencoder.py
clustpy/deep/neural_networks/_resnet_ae_modules.py
clustpy/deep/neural_networks/convolutional_autoencoder.py
clustpy/deep/neural_networks/feedforward_autoencoder.py
clustpy/deep/neural_networks/neighbor_encoder.py
clustpy/deep/neural_networks/stacked_autoencoder.py
clustpy/deep/neural_networks/variational_autoencoder.py
clustpy/density/__init__.py
clustpy/density/multi_density_dbscan.py
clustpy/hierarchical/__init__.py
clustpy/hierarchical/_cluster_tree.py
clustpy/hierarchical/diana.py
clustpy/metrics/__init__.py
clustpy/metrics/clustering_metrics.py
clustpy/metrics/confusion_matrix.py
clustpy/metrics/hierarchical_metrics.py
clustpy/metrics/multipe_labelings_scoring.py
clustpy/metrics/pair_counting_scores.py
clustpy/partition/__init__.py
clustpy/partition/dipext.py
clustpy/partition/dipmeans.py
