Metadata-Version: 2.1
Name: clustpy
Version: 0.0.2
Summary: A Python library for advanced clustering algorithms
Home-page: https://clustpy.readthedocs.io/en/latest/
Author: Collin Leiber
Author-email: leiber@dbs.ifi.lmu.de
License: BSD-3-Clause License
Requires-Python: >=3.10
License-File: LICENSE
Requires-Dist: numpy
Requires-Dist: scipy
Requires-Dist: scikit-learn
Requires-Dist: matplotlib
Requires-Dist: torch
Requires-Dist: pandas
Requires-Dist: tqdm
Provides-Extra: full
Requires-Dist: torchvision; extra == "full"
Requires-Dist: Pillow; extra == "full"
Requires-Dist: nltk; extra == "full"
Requires-Dist: xlrd; extra == "full"
Requires-Dist: opencv-python; extra == "full"
Requires-Dist: requests; extra == "full"
